overture/__init__.py
overture/errors.py
overture/predictions.py
overture_sdk-0.0.8.dist-info/LICENSE.txt
overture_sdk-0.0.8.dist-info/METADATA
overture_sdk-0.0.8.dist-info/RECORD
overture_sdk-0.0.8.dist-info/WHEEL
overture_sdk-0.0.8.dist-info/top_level.txt
